{"inkVersion":20,"root":[["\n","^player: Convenient that I can't jump, life would be easier if we could group up in this damn place... ",{"#":"speaker:Player"},"\n","^friend: yeah I've noticed it too, it's like we're really the characters from GAMENAME. ",{"#":"speaker:Friend"},"\n","^player: do you remember what the game was about? ",{"#":"speaker:Player"},"\n",{"#":"playCutscene"},"^friend: the darkness, it's moving towards us… it's closing in on us ",{"#":"speaker:Friend"},"\n","^friend: I think we need to continue forward and try and find a way out ",{"#":"speaker:Friend"},"\n","^player: okay good idea… ",{"#":"speaker:Player"},"\n",["done",{"#f":5,"#n":"g-0"}],null],"done",{"global decl":["ev",0,{"VAR=":"friendship_meter"},true,{"VAR=":"firstTime"},false,{"VAR=":"hasMedkit"},false,{"VAR=":"giveMedkit"},"str","^beforeZombie1","/str",{"VAR=":"section"},"/ev","end",null],"#f":1}],"listDefs":{}}